ioriver/__init__.py
ioriver/key_info.py
ioriver/policy.py
ioriver/url_signer.py
tests/__init__.py
tests/test_basic_policy.py
tests/test_url_signer.py
tests/test_util.py
url_signer_python-0.4.0.dist-info/METADATA
url_signer_python-0.4.0.dist-info/WHEEL
url_signer_python-0.4.0.dist-info/top_level.txt
url_signer_python-0.4.0.dist-info/RECORD
