Metadata-Version: 2.4
Name: url-signer-python
Version: 0.4.0
Summary: IO River python library for generating URL signatures
Author: IO River
Author-email: support@ioriver.io
Requires-Python: >=3.9
Requires-Dist: akamai-edgeauth>=0.3.2
Requires-Dist: cryptography>=44.0.0
Dynamic: author
Dynamic: author-email
Dynamic: requires-python
